MVVLive/MVVLive.py
MVVLive/__init__.py
MVVLive-1.0.2.dist-info/METADATA
MVVLive-1.0.2.dist-info/WHEEL
MVVLive-1.0.2.dist-info/top_level.txt
MVVLive-1.0.2.dist-info/RECORD
