Metadata-Version: 2.1
Name: MVVLive
Version: 1.0.2
Summary: Live public transportation data for Munich public transport
Home-page: https://github.com/darioschmid/PyMVVLive
Author: Dario Schmid
Author-email: darioschmid99@outlook.com
License: ?
Requires-Dist: soupsieve ==2.5
Requires-Dist: beautifulsoup4 ==4.12.2
Requires-Dist: requests
Requires-Dist: pathlib
